web_to_markdown/__init__.py
web_to_markdown/cli.py
web_to_markdown/converter.py
web_to_markdown/crawler.py
web_to_markdown-0.1.0.dist-info/LICENSE
web_to_markdown-0.1.0.dist-info/METADATA
web_to_markdown-0.1.0.dist-info/WHEEL
web_to_markdown-0.1.0.dist-info/entry_points.txt
web_to_markdown-0.1.0.dist-info/top_level.txt
web_to_markdown-0.1.0.dist-info/RECORD
