Metadata-Version: 2.2
Name: web-to-markdown
Version: 0.1.0
Summary: A Python library for crawling web pages and converting them to markdown format
Home-page: https://github.com/roger_koa/web-to-markdown
Author: Roger Koa
License: MIT
Project-URL: Homepage, https://github.com/roger_koa/web-to-markdown
Project-URL: Repository, https://github.com/roger_koa/web-to-markdown.git
Keywords: web,crawler,markdown,converter,html
Classifier: Development Status :: 4 - Beta
Classifier: Intended Audience :: Developers
Classifier: License :: OSI Approved :: MIT License
Classifier: Operating System :: OS Independent
Classifier: Programming Language :: Python :: 3
Classifier: Programming Language :: Python :: 3.8
Classifier: Programming Language :: Python :: 3.9
Classifier: Programming Language :: Python :: 3.10
Classifier: Programming Language :: Python :: 3.11
Requires-Python: >=3.8
License-File: LICENSE
Requires-Dist: beautifulsoup4>=4.12.0
Requires-Dist: requests>=2.31.0
Requires-Dist: urllib3>=2.1.0
Requires-Dist: markdown>=3.5.0
Requires-Dist: readability-lxml>=0.8.1
Requires-Dist: html2text>=2020.1.16
Dynamic: home-page
Dynamic: requires-dist
Dynamic: requires-python
